{
  "timestamp": "2025-07-10 22:42:03",
  "config": {
    "max_samples": 50000,
    "embedding": null,
    "quick_mode": false,
    "save_results": true,
    "comparative_analysis": true
  },
  "datasets_analyzed": 7,
  "total_time": 2.0059046745300293,
  "results": [
    {
      "dataset_name": "algebraic_features_up_to_5000",
      "dataset_type": "ml",
      "shape": [
        4994,
        42
      ],
      "positive_rate": 0.029635562675210253,
      "feature_count": 41,
      "model_performance": {
        "logistic": {
          "train_acc": 1.0,
          "test_acc": 1.0,
          "test_auc": 1.0
        },
        "random_forest": {
          "train_acc": 1.0,
          "test_acc": 1.0,
          "test_auc": 1.0
        },
        "gradient_boost": {
          "train_acc": 1.0,
          "test_acc": 1.0,
          "test_auc": 1.0
        }
      },
      "top_features": [
        {
          "feature": "is_member",
          "importance": 0.6907911308037874
        },
        {
          "feature": "sqrt_number",
          "importance": 0.034180683391444894
        },
        {
          "feature": "log_number",
          "importance": 0.03345622881357039
        },
        {
          "feature": "totient",
          "importance": 0.02729431167279468
        },
        {
          "feature": "number",
          "importance": 0.025670979778154756
        },
        {
          "feature": "mod_11",
          "importance": 0.02042208014470696
        },
        {
          "feature": "digit_product",
          "importance": 0.018927509211694473
        },
        {
          "feature": "digit_count",
          "importance": 0.01759905777163545
        },
        {
          "feature": "alternating_digit_sum",
          "importance": 0.014695013989049308
        },
        {
          "feature": "sum_of_proper_divisors",
          "importance": 0.01209541931328017
        }
      ],
      "analysis_time": 1752180122.448498
    },
    {
      "dataset_name": "digit_tensor_4d_up_to_5000",
      "dataset_type": "ml",
      "shape": [
        4994,
        14
      ],
      "positive_rate": 0.029635562675210253,
      "feature_count": 13,
      "model_performance": {
        "logistic": {
          "train_acc": 1.0,
          "test_acc": 1.0,
          "test_auc": 1.0
        },
        "random_forest": {
          "train_acc": 1.0,
          "test_acc": 1.0,
          "test_auc": 1.0
        },
        "gradient_boost": {
          "train_acc": 1.0,
          "test_acc": 1.0,
          "test_auc": 1.0
        }
      },
      "top_features": [
        {
          "feature": "is_palindrome",
          "importance": 0.7805168019958295
        },
        {
          "feature": "number",
          "importance": 0.04984543582471014
        },
        {
          "feature": "alternating_sum",
          "importance": 0.03434380929651898
        },
        {
          "feature": "has_repeating_digits",
          "importance": 0.03396633899034757
        },
        {
          "feature": "digit_count",
          "importance": 0.028412176505158638
        },
        {
          "feature": "last_digit",
          "importance": 0.014273067099913016
        },
        {
          "feature": "digit_product",
          "importance": 0.013835075909003656
        },
        {
          "feature": "digit_pos_2",
          "importance": 0.009033407563308005
        },
        {
          "feature": "first_digit",
          "importance": 0.008634948259014334
        },
        {
          "feature": "digit_pos_0",
          "importance": 0.008046649242685961
        }
      ],
      "analysis_time": 1752180122.7985754
    },
    {
      "dataset_name": "digit_tensor_6d_with_embeddings_up_to_5000",
      "dataset_type": "ml",
      "shape": [
        4994,
        27
      ],
      "positive_rate": 0.029635562675210253,
      "feature_count": 26,
      "model_performance": {
        "logistic": {
          "train_acc": 1.0,
          "test_acc": 1.0,
          "test_auc": 1.0
        },
        "random_forest": {
          "train_acc": 1.0,
          "test_acc": 1.0,
          "test_auc": 1.0
        },
        "gradient_boost": {
          "train_acc": 1.0,
          "test_acc": 1.0,
          "test_auc": 1.0
        }
      },
      "top_features": [
        {
          "feature": "is_palindrome",
          "importance": 0.6921636393821613
        },
        {
          "feature": "has_repeating_digits",
          "importance": 0.04531733457423522
        },
        {
          "feature": "number",
          "importance": 0.04400170024073021
        },
        {
          "feature": "pca_0",
          "importance": 0.034648349890685895
        },
        {
          "feature": "digit_count",
          "importance": 0.02660823301736716
        },
        {
          "feature": "fourier_2",
          "importance": 0.02062599062016173
        },
        {
          "feature": "alternating_sum",
          "importance": 0.01570855125565432
        },
        {
          "feature": "fourier_6",
          "importance": 0.015471980712681554
        },
        {
          "feature": "last_digit",
          "importance": 0.014961203954020478
        },
        {
          "feature": "fourier_5",
          "importance": 0.013042416736465525
        }
      ],
      "analysis_time": 1752180123.2397401
    },
    {
      "dataset_name": "prefix_2d_suffix_1d_up_to_5000",
      "dataset_type": "matrix",
      "shape": [
        90,
        9
      ],
      "total_cells": 810,
      "positive_cells": 90,
      "positive_rate": 0.1111111111111111,
      "row_stats": {
        "count": 90.0,
        "mean": 1.0,
        "std": 0.0,
        "min": 1.0,
        "25%": 1.0,
        "50%": 1.0,
        "75%": 1.0,
        "max": 1.0
      },
      "col_stats": {
        "count": 9.0,
        "mean": 10.0,
        "std": 0.0,
        "min": 10.0,
        "25%": 10.0,
        "50%": 10.0,
        "75%": 10.0,
        "max": 10.0
      },
      "best_rows": {
        "10": 1,
        "11": 1,
        "12": 1,
        "13": 1,
        "14": 1
      },
      "best_cols": {
        "1": 10,
        "2": 10,
        "3": 10,
        "4": 10,
        "5": 10
      },
      "analysis_time": 1752180123.246478
    },
    {
      "error": "index 0 is out of bounds for axis 0 with size 0",
      "dataset": "prefix_3d_suffix_2d_up_to_5000"
    },
    {
      "dataset_name": "sequence_patterns_w10_up_to_5000",
      "dataset_type": "ml",
      "shape": [
        4994,
        11
      ],
      "positive_rate": 0.029635562675210253,
      "feature_count": 10,
      "model_performance": {
        "logistic": {
          "train_acc": 1.0,
          "test_acc": 0.998998998998999,
          "test_auc": 0.9999312005503956
        },
        "random_forest": {
          "train_acc": 1.0,
          "test_acc": 1.0,
          "test_auc": 1.0
        },
        "gradient_boost": {
          "train_acc": 1.0,
          "test_acc": 1.0,
          "test_auc": 1.0
        }
      },
      "top_features": [
        {
          "feature": "avg_recent_diff",
          "importance": 0.39204255908654223
        },
        {
          "feature": "growth_ratio",
          "importance": 0.3622761570728812
        },
        {
          "feature": "local_density",
          "importance": 0.1178608084766542
        },
        {
          "feature": "prev_gap",
          "importance": 0.06554214745908665
        },
        {
          "feature": "next_gap",
          "importance": 0.031153460981968174
        },
        {
          "feature": "number",
          "importance": 0.013138271227158153
        },
        {
          "feature": "members_before",
          "importance": 0.010283297549946512
        },
        {
          "feature": "members_after",
          "importance": 0.0069113280914994335
        },
        {
          "feature": "in_cluster",
          "importance": 0.0007919700542635197
        },
        {
          "feature": "is_isolated",
          "importance": 0.0
        }
      ],
      "analysis_time": 1752180123.5957434
    },
    {
      "dataset_name": "sequence_patterns_w5_up_to_5000",
      "dataset_type": "ml",
      "shape": [
        4994,
        11
      ],
      "positive_rate": 0.029635562675210253,
      "feature_count": 10,
      "model_performance": {
        "logistic": {
          "train_acc": 1.0,
          "test_acc": 0.998998998998999,
          "test_auc": 1.0
        },
        "random_forest": {
          "train_acc": 1.0,
          "test_acc": 1.0,
          "test_auc": 1.0
        },
        "gradient_boost": {
          "train_acc": 1.0,
          "test_acc": 1.0,
          "test_auc": 1.0
        }
      },
      "top_features": [
        {
          "feature": "avg_recent_diff",
          "importance": 0.4143090500852621
        },
        {
          "feature": "growth_ratio",
          "importance": 0.41276025330438076
        },
        {
          "feature": "prev_gap",
          "importance": 0.06613073400415709
        },
        {
          "feature": "next_gap",
          "importance": 0.05420112834125091
        },
        {
          "feature": "number",
          "importance": 0.016065089498920843
        },
        {
          "feature": "members_before",
          "importance": 0.012405153322429547
        },
        {
          "feature": "local_density",
          "importance": 0.011021605316783362
        },
        {
          "feature": "members_after",
          "importance": 0.009322620649951286
        },
        {
          "feature": "in_cluster",
          "importance": 0.003467095730779553
        },
        {
          "feature": "is_isolated",
          "importance": 0.0003172697460846807
        }
      ],
      "analysis_time": 1752180123.9768925
    }
  ]
}